aliro_honeywell/__init__.py
aliro_honeywell/api_client.py
aliro_honeywell/configuration.py
aliro_honeywell/exceptions.py
aliro_honeywell/rest.py
aliro_honeywell/api/__init__.py
aliro_honeywell/api/authentication_api.py
aliro_honeywell/api/job_api.py
aliro_honeywell/api/machine_api.py
aliro_honeywell/api/metering_api.py
aliro_honeywell/models/__init__.py
aliro_honeywell/models/error_response.py
aliro_honeywell/models/error_response_error.py
aliro_honeywell/models/inline_response200.py
aliro_honeywell/models/inline_response2001.py
aliro_honeywell/models/inline_response2002.py
aliro_honeywell/models/inline_response2003.py
aliro_honeywell/models/inline_response2003_jobs.py
aliro_honeywell/models/inline_response_default.py
aliro_honeywell/models/inline_response_default1.py
aliro_honeywell/models/job_post_parameters.py
aliro_honeywell/models/job_response.py
aliro_honeywell/models/login_post_parameters.py
aliro_honeywell-1.0.1.dist-info/METADATA
aliro_honeywell-1.0.1.dist-info/WHEEL
aliro_honeywell-1.0.1.dist-info/top_level.txt
aliro_honeywell-1.0.1.dist-info/RECORD
